README.rst
setup.py
braillegraph/__init__.py
braillegraph/__main__.py
braillegraph/braillegraph.py
braillegraph.egg-info/PKG-INFO
braillegraph.egg-info/SOURCES.txt
braillegraph.egg-info/dependency_links.txt
braillegraph.egg-info/not-zip-safe
braillegraph.egg-info/top_level.txt