Metadata-Version: 1.1
Name: braillegraph
Version: 0.6
Summary: A library for creating graphs using Unicode braille characters
Home-page: http://github.com/chrisbouchard/braillegraph
Author: Chris Bouchard
Author-email: chris@upliftinglemma.net
License: UNKNOWN
Platform: UNKNOWN
Classifier: Development Status :: 4 - Beta
Classifier: Environment :: Console
Classifier: Intended Audience :: End Users/Desktop
Classifier: License :: OSI Approved :: BSD License
Classifier: Natural Language :: English
Classifier: Operating System :: POSIX
Classifier: Programming Language :: Python :: 3 :: Only
Classifier: Topic :: Utilities
